CHANGES.txt
COPYRIGHT.txt
LICENSE.txt
README.txt
bootstrap.py
setup.py
profiles/base.cfg
src/gocept/__init__.py
src/gocept.paypal.egg-info/PKG-INFO
src/gocept.paypal.egg-info/SOURCES.txt
src/gocept.paypal.egg-info/dependency_links.txt
src/gocept.paypal.egg-info/not-zip-safe
src/gocept.paypal.egg-info/requires.txt
src/gocept.paypal.egg-info/top_level.txt
src/gocept/paypal/__init__.py
src/gocept/paypal/interfaces.py
src/gocept/paypal/paypal.py
src/gocept/paypal/paypal.txt
src/gocept/paypal/tests.py