Metadata-Version: 1.0
Name: gocept.paypal
Version: 0.1.10
Summary: Paypal Utility providing the paypal API
Home-page: http://pypi.python.org/pypi/gocept.paypal/
Author: Sebastian Wehrmann, Daniel Havlik
Author-email: sw@gocept.com
License: ZPL 2.1
Keywords: zope3 gocept paypal
Platform: UNKNOWN
Classifier: Development Status :: 4 - Beta
Classifier: Environment :: Web Environment
Classifier: Intended Audience :: Developers
Classifier: License :: OSI Approved :: Zope Public License
Classifier: Programming Language :: Python
Classifier: Natural Language :: English
Classifier: Operating System :: OS Independent
Classifier: Topic :: Internet :: WWW/HTTP
